provider/__init__.py
provider/api/__init__.py
provider/api/models.py
provider/api/routes.py
provider/config.py
provider/container.py
provider/data/deployments/l2.json
provider/discovery/__init__.py
provider/discovery/advertiser.py
provider/discovery/golem_base_advertiser.py
provider/discovery/golem_base_utils.py
provider/discovery/multi_advertiser.py
provider/discovery/resource_monitor.py
provider/discovery/resource_tracker.py
provider/discovery/service.py
provider/jobs/store.py
provider/main.py
provider/network/port_verifier.py
provider/payments/blockchain_service.py
provider/payments/monitor.py
provider/payments/stream_map.py
provider/security/ethereum.py
provider/security/faucet.py
provider/security/l2_faucet.py
provider/service.py
provider/utils/__init__.py
provider/utils/ascii_art.py
provider/utils/logging.py
provider/utils/port_display.py
provider/utils/pricing.py
provider/utils/retry.py
provider/utils/setup.py
provider/vm/__init__.py
provider/vm/cloud_init.py
provider/vm/models.py
provider/vm/multipass.py
provider/vm/multipass_adapter.py
provider/vm/name_mapper.py
provider/vm/port_manager.py
provider/vm/provider.py
provider/vm/proxy_manager.py
provider/vm/service.py
golem_vm_provider-0.1.63.dist-info/METADATA
golem_vm_provider-0.1.63.dist-info/WHEEL
golem_vm_provider-0.1.63.dist-info/entry_points.txt
golem_vm_provider-0.1.63.dist-info/RECORD
