Metadata-Version: 2.3
Name: golem-vm-provider
Version: 0.1.63
Summary: VM on Golem Provider Node - Run your own provider node to offer VMs on the Golem Network
Keywords: golem,vm,provider,cloud,decentralized
Author: Phillip Jensen
Author-email: phillip+vm-on-golem@golemgrid.com
Requires-Python: >=3.11,<4.0
Classifier: Development Status :: 4 - Beta
Classifier: Environment :: Console
Classifier: Intended Audience :: System Administrators
Classifier: Operating System :: POSIX :: Linux
Classifier: Programming Language :: Python :: 3
Classifier: Programming Language :: Python :: 3.11
Classifier: Programming Language :: Python :: 3.12
Classifier: Programming Language :: Python :: 3.13
Classifier: Programming Language :: Python :: 3.9
Classifier: Topic :: System :: Distributed Computing
Requires-Dist: aiohttp (>=3.8.1,<4.0.0)
Requires-Dist: colorlog (>=6.8.0,<7.0.0)
Requires-Dist: cryptography (>=3.4.7,<4.0.0)
Requires-Dist: dependency-injector (>=4.41.0,<5.0.0)
Requires-Dist: eth-account (>=0.13.6,<0.14.0)
Requires-Dist: fastapi (>=0.103.0,<0.104.0)
Requires-Dist: golem-base-sdk (==0.1.0)
Requires-Dist: golem-faucet (>=0.1.0,<0.2.0)
Requires-Dist: golem-streaming-abi (>=0.1.0,<0.2.0)
Requires-Dist: httpx (>=0.23.0,<0.24.0)
Requires-Dist: psutil (>=5.9.0,<6.0.0)
Requires-Dist: pydantic (>=2.4.0,<3.0.0)
Requires-Dist: pydantic-settings (>=2.1.0,<3.0.0)
Requires-Dist: python-dotenv (>=1.0.0,<2.0.0)
Requires-Dist: python-jose[cryptography] (>=3.3.0,<4.0.0)
Requires-Dist: python-multipart (>=0.0.5,<0.0.6)
Requires-Dist: pyyaml (>=6.0.1,<7.0.0)
Requires-Dist: requests (>=2.31.0,<3.0.0)
Requires-Dist: rich (>=13.7.0,<14.0.0)
Requires-Dist: setuptools (>=69.0.3,<70.0.0)
Requires-Dist: typer (>=0.9.0,<1.0.0)
Requires-Dist: uvicorn (>=0.15.0,<0.16.0)
Requires-Dist: web3 (==7.13.0)
Project-URL: Homepage, https://github.com/cryptobench/vm-on-golem
Project-URL: Repository, https://github.com/cryptobench/vm-on-golem
